morsewave.py
morsewave-1.0.dist-info/LICENSE
morsewave-1.0.dist-info/METADATA
morsewave-1.0.dist-info/WHEEL
morsewave-1.0.dist-info/top_level.txt
morsewave-1.0.dist-info/RECORD
