Metadata-Version: 2.1
Name: morsewave
Version: 1.0
Summary: All-in-one solution for converting between text and Morse code effortlessly
Author-email: Tomas Illuminati <tomiluminati@gmail.com>
Project-URL: Homepage, https://github.com/tomasilluminati/MorseWave
Project-URL: Issues, https://github.com/tomasilluminati/MorseWave/issues
Classifier: Programming Language :: Python :: 3
Classifier: License :: OSI Approved :: MIT License
Classifier: Operating System :: OS Independent
Requires-Python: >=3.11
License-File: LICENSE
